{
  "activityId": 21388047885,
  "activityName": "Base",
  "startTimeLocal": "2025-12-29 17:12:50",
  "startTimeGMT": "2025-12-29 23:12:50",
  "activityType": {
    "typeId": 1,
    "typeKey": "running",
    "parentTypeId": 17,
    "isHidden": false,
    "restricted": false,
    "trimmable": true
  },
  "eventType": {
    "typeId": 9,
    "typeKey": "uncategorized",
    "sortOrder": 10
  },
  "distance": 5322.14013671875,
  "duration": 2159.368896484375,
  "elapsedDuration": 2159.368896484375,
  "movingDuration": 2149.0,
  "elevationGain": 0.0,
  "elevationLoss": 3.0,
  "averageSpeed": 2.4649999141693115,
  "maxSpeed": 3.86299991607666,
  "hasPolyline": false,
  "hasImages": false,
  "ownerId": 139472598,
  "ownerDisplayName": "8ccedb6a-587d-4ea7-8d8c-d75a177bd0d8",
  "ownerFullName": "Sandeep Reddy Alalla",
  "ownerProfileImageUrlSmall": "https://connect.garmin.com/images/avatars/avatar_a05493a5-0c0b-450a-89e0-62823066f92f_s.png",
  "ownerProfileImageUrlMedium": "https://connect.garmin.com/images/avatars/avatar_a05493a5-0c0b-450a-89e0-62823066f92f_m.png",
  "ownerProfileImageUrlLarge": "https://connect.garmin.com/images/avatars/avatar_a05493a5-0c0b-450a-89e0-62823066f92f.png",
  "calories": 336.0,
  "bmrCalories": 49.0,
  "averageHR": 155.0,
  "maxHR": 170.0,
  "averageRunningCadenceInStepsPerMinute": 163.421875,
  "maxRunningCadenceInStepsPerMinute": 174.0,
  "steps": 5882,
  "userRoles": [
    "SCOPE_GOLF_API_READ",
    "SCOPE_DI_OAUTH_2_CREATE_DI_USER",
    "SCOPE_ATP_READ",
    "SCOPE_DIVE_API_WRITE",
    "SCOPE_COMMUNITY_COURSE_ADMIN_READ",
    "SCOPE_DIVE_API_READ",
    "SCOPE_DI_OAUTH_2_CLIENT_READ",
    "SCOPE_CONNECT_WRITE",
    "SCOPE_COMMUNITY_COURSE_WRITE",
    "SCOPE_CONNECT_MCT_DAILY_LOG_READ",
    "SCOPE_CONNECT_API_CREATE_UPDATE_USER",
    "SCOPE_MESSAGE_GENERATION_READ",
    "SCOPE_DI_OAUTH_2_CLIENT_REVOCATION_ADMIN",
    "SCOPE_CONNECT_WEB_TEMPLATE_RENDER",
    "SCOPE_OMT_SUBSCRIPTION_ADMIN_READ",
    "SCOPE_DI_OAUTH_2_MANAGED_STATUS_ADMIN_WRITE",
    "SCOPE_CONNECT_NON_SOCIAL_SHARED_READ",
    "SCOPE_CONNECT_READ",
    "SCOPE_DI_OAUTH_2_PRERELEASE_PERMISSIONS_ADMIN_WRITE",
    "SCOPE_DI_OAUTH_2_TOKEN_ADMIN",
    "ROLE_CONNECTUSER",
    "ROLE_FITNESS_USER",
    "ROLE_WELLNESS_USER",
    "ROLE_OUTDOOR_USER"
  ],
  "privacy": {
    "typeId": 2,
    "typeKey": "private"
  },
  "userPro": false,
  "hasVideo": false,
  "timeZoneId": 152,
  "beginTimestamp": 1767049970000,
  "sportTypeId": 1,
  "avgPower": 246.0,
  "maxPower": 403.0,
  "aerobicTrainingEffect": 3.5999999046325684,
  "anaerobicTrainingEffect": 0.0,
  "normPower": 249.0,
  "avgVerticalOscillation": 8.630000305175782,
  "avgGroundContactTime": 283.20001220703125,
  "avgStrideLength": 90.77999877929688,
  "avgVerticalRatio": 9.550000190734863,
  "workoutId": 3613066937,
  "deviceId": 3613066937,
  "minElevation": 405.79998779296875,
  "maxElevation": 409.6000061035156,
  "maxDoubleCadence": 174.0,
  "summarizedDiveInfo": {
    "summarizedDiveGases": []
  },
  "maxVerticalSpeed": 0.20001220703125003,
  "manufacturer": "GARMIN",
  "lapCount": 4,
  "waterEstimated": 599.0,
  "trainingEffectLabel": "TEMPO",
  "activityTrainingLoad": 114.30961608886719,
  "minActivityLapDuration": 359.3689880371094,
  "aerobicTrainingEffectMessage": "IMPROVING_AEROBIC_FITNESS_2",
  "anaerobicTrainingEffectMessage": "NO_ANAEROBIC_BENEFIT_0",
  "splitSummaries": [
    {
      "distance": 1.73,
      "duration": 1.0,
      "elevationGain": 0.0,
      "elevationLoss": 0.0,
      "averageSpeed": 1.72599995136261,
      "maxSpeed": 1.72599995136261,
      "calories": 0.0,
      "bmrCalories": 0.0,
      "averageHR": 156.0,
      "maxHR": 156.0,
      "averageRunCadence": 160.0,
      "maxRunCadence": 160.0,
      "averagePower": 130.0,
      "maxPower": 130.0,
      "normalizedPower": 193.0,
      "strideLength": 84.80000000000001,
      "verticalOscillation": 6.129999923706055,
      "verticalRatio": 7.21999979019165,
      "totalExerciseReps": 0,
      "avgVerticalSpeed": 0.0,
      "splitType": "RWD_WALK",
      "noOfSplits": 1,
      "maxElevationGain": 0.0,
      "averageElevationGain": 0.0,
      "maxDistance": 1,
      "maxDistanceWithPrecision": 1.73,
      "avgStepFrequency": 160.0,
      "avgStepLength": 848.0
    },
    {
      "distance": 5322.13,
      "duration": 2159.369,
      "movingDuration": 2148.0,
      "elevationGain": 0.0,
      "elevationLoss": 3.0,
      "averageSpeed": 2.4649999141693115,
      "averageMovingSpeed": 2.477714098143622,
      "maxSpeed": 3.86299991607666,
      "calories": 336.0,
      "bmrCalories": 49.0,
      "averageHR": 155.0,
      "maxHR": 170.0,
      "averageRunCadence": 163.421875,
      "maxRunCadence": 174.0,
      "averagePower": 246.0,
      "maxPower": 403.0,
      "normalizedPower": 249.0,
      "groundContactTime": 283.20001220703125,
      "strideLength": 90.77999877929688,
      "verticalOscillation": 8.630000305175782,
      "verticalRatio": 9.550000190734863,
      "totalExerciseReps": 0,
      "avgVerticalSpeed": 0.0,
      "splitType": "INTERVAL_ACTIVE",
      "noOfSplits": 1,
      "maxElevationGain": 0.0,
      "averageElevationGain": 0.0,
      "maxDistance": 5322,
      "maxDistanceWithPrecision": 5322.13,
      "avgStepFrequency": 163.421875,
      "avgStepLength": 907.7999877929688
    },
    {
      "distance": 0.0,
      "duration": 5.001,
      "movingDuration": 0.0,
      "elevationGain": 0.0,
      "elevationLoss": 0.0,
      "averageSpeed": 0.0,
      "maxSpeed": 0.0,
      "calories": 0.0,
      "bmrCalories": 0.0,
      "averageHR": 88.0,
      "maxHR": 89.0,
      "averageRunCadence": 31.59375,
      "maxRunCadence": 158.0,
      "averagePower": 0.0,
      "maxPower": 0.0,
      "strideLength": 0.0,
      "totalExerciseReps": 0,
      "avgVerticalSpeed": 0.0,
      "splitType": "RWD_STAND",
      "noOfSplits": 2,
      "maxElevationGain": 0.0,
      "averageElevationGain": 0.0,
      "maxDistance": 0,
      "maxDistanceWithPrecision": 0.0,
      "avgStepFrequency": 31.59375
    },
    {
      "distance": 5320.41,
      "duration": 2153.35,
      "movingDuration": 2145.35,
      "elevationGain": 0.0,
      "elevationLoss": 3.0,
      "averageSpeed": 2.4709999561309814,
      "averageMovingSpeed": 2.4798651215820167,
      "maxSpeed": 3.86299991607666,
      "calories": 335.0,
      "bmrCalories": 49.0,
      "averageHR": 155.0,
      "maxHR": 170.0,
      "averageRunCadence": 163.71875,
      "maxRunCadence": 174.0,
      "averagePower": 247.0,
      "maxPower": 403.0,
      "normalizedPower": 249.0,
      "groundContactTime": 283.20001220703125,
      "strideLength": 90.77999877929688,
      "verticalOscillation": 8.630000305175782,
      "verticalRatio": 9.550000190734863,
      "totalExerciseReps": 0,
      "avgVerticalSpeed": 0.0,
      "splitType": "RWD_RUN",
      "noOfSplits": 2,
      "maxElevationGain": 0.0,
      "averageElevationGain": 0.0,
      "maxDistance": 4404,
      "maxDistanceWithPrecision": 4404.33,
      "avgStepFrequency": 163.71875,
      "avgStepLength": 907.7999877929688
    }
  ],
  "hasSplits": true,
  "moderateIntensityMinutes": 2,
  "vigorousIntensityMinutes": 33,
  "differenceBodyBattery": -9,
  "hasHeatMap": false,
  "fastestSplit_1000": 385.5790100097656,
  "fastestSplit_1609": 622.3189697265625,
  "fastestSplit_5000": 2006.8599853515625,
  "hrTimeInZone_1": 16.0,
  "hrTimeInZone_2": 43.004,
  "hrTimeInZone_3": 687.0,
  "hrTimeInZone_4": 1403.983,
  "hrTimeInZone_5": 0.0,
  "powerTimeInZone_1": 196.982,
  "powerTimeInZone_2": 586.994,
  "powerTimeInZone_3": 592.092,
  "powerTimeInZone_4": 731.94,
  "powerTimeInZone_5": 32.004,
  "endTimeGMT": "2025-12-29 23:48:49",
  "qualifyingDive": false,
  "purposeful": false,
  "manualActivity": false,
  "decoDive": false,
  "elevationCorrected": false,
  "atpActivity": false,
  "autoCalcCalories": false,
  "favorite": false,
  "parent": false,
  "pr": true,
  "activityUUID": {
    "uuid": "2cea5d5d-a974-4b8e-aedb-a75b3b3931f8"
  },
  "userProfileId": 139472598,
  "isMultiSportParent": false,
  "activityTypeDTO": {
    "typeId": 1,
    "typeKey": "running",
    "parentTypeId": 17,
    "isHidden": false,
    "restricted": false,
    "trimmable": true
  },
  "eventTypeDTO": {
    "typeId": 9,
    "typeKey": "uncategorized",
    "sortOrder": 10
  },
  "accessControlRuleDTO": {
    "typeId": 2,
    "typeKey": "private"
  },
  "timeZoneUnitDTO": {
    "unitId": 152,
    "unitKey": "America/Chicago",
    "factor": 0.0,
    "timeZone": "America/Chicago"
  },
  "metadataDTO": {
    "isOriginal": true,
    "deviceApplicationInstallationId": 1001900,
    "agentApplicationInstallationId": null,
    "agentString": null,
    "fileFormat": {
      "formatId": 7,
      "formatKey": "fit"
    },
    "associatedCourseId": null,
    "lastUpdateDate": "2025-12-30T00:08:04.0",
    "uploadedDate": "2025-12-30T00:08:03.0",
    "videoUrl": null,
    "hasPolyline": false,
    "hasChartData": true,
    "hasHrTimeInZones": true,
    "hasPowerTimeInZones": true,
    "userInfoDto": {
      "userProfilePk": 139472598,
      "displayname": "8ccedb6a-587d-4ea7-8d8c-d75a177bd0d8",
      "fullname": "Sandeep Reddy Alalla",
      "profileImageUrlLarge": "https://connect.garmin.com/images/avatars/avatar_a05493a5-0c0b-450a-89e0-62823066f92f.png",
      "profileImageUrlMedium": "https://connect.garmin.com/images/avatars/avatar_a05493a5-0c0b-450a-89e0-62823066f92f_m.png",
      "profileImageUrlSmall": "https://connect.garmin.com/images/avatars/avatar_a05493a5-0c0b-450a-89e0-62823066f92f_s.png",
      "userPro": false
    },
    "childIds": [],
    "childActivityTypes": [],
    "sensors": null,
    "activityImages": [],
    "manufacturer": "GARMIN",
    "diveNumber": null,
    "lapCount": 4,
    "associatedWorkoutId": 3613066937,
    "isAtpActivity": null,
    "deviceMetaDataDTO": {
      "deviceId": "3613066937",
      "deviceTypePk": 37086,
      "deviceVersionPk": 1001900
    },
    "hasIntensityIntervals": false,
    "hasSplits": true,
    "eBikeMaxAssistModes": null,
    "eBikeBatteryUsage": null,
    "eBikeBatteryRemaining": null,
    "eBikeAssistModeInfoDTOList": null,
    "hasRunPowerWindData": false,
    "calendarEventInfo": null,
    "groupRideUUID": null,
    "hasHeatMap": false,
    "personalRecord": true,
    "gcj02": false,
    "runPowerWindDataEnabled": true,
    "elevationCorrected": false,
    "autoCalcCalories": false,
    "favorite": false,
    "trimmed": false,
    "manualActivity": false
  },
  "summaryDTO": {
    "startTimeLocal": "2025-12-29T17:12:50.0",
    "startTimeGMT": "2025-12-29T23:12:50.0",
    "distance": 5322.14,
    "duration": 2159.369,
    "movingDuration": 2149.0,
    "elapsedDuration": 2159.369,
    "elevationGain": 0.0,
    "elevationLoss": 3.0,
    "maxElevation": 409.6,
    "minElevation": 405.8,
    "averageSpeed": 2.4649999141693115,
    "averageMovingSpeed": 2.4765659081985807,
    "maxSpeed": 3.86299991607666,
    "calories": 336.0,
    "bmrCalories": 49.0,
    "averageHR": 155.0,
    "maxHR": 170.0,
    "minHR": 88.0,
    "averageRunCadence": 163.421875,
    "maxRunCadence": 174.0,
    "averagePower": 246.0,
    "maxPower": 403.0,
    "minPower": 0.0,
    "normalizedPower": 249.0,
    "totalWork": 127.20703003804279,
    "groundContactTime": 283.20001220703125,
    "strideLength": 90.77999877929688,
    "verticalOscillation": 8.630000305175782,
    "trainingEffect": 3.5999999046325684,
    "anaerobicTrainingEffect": 0.0,
    "aerobicTrainingEffectMessage": "IMPROVING_AEROBIC_FITNESS_2",
    "anaerobicTrainingEffectMessage": "NO_ANAEROBIC_BENEFIT_0",
    "verticalRatio": 9.550000190734863,
    "maxVerticalSpeed": 0.20001220703125003,
    "waterEstimated": 599.0,
    "trainingEffectLabel": "TEMPO",
    "activityTrainingLoad": 114.30961608886719,
    "minActivityLapDuration": 359.369,
    "directWorkoutFeel": 50,
    "directWorkoutRpe": 30,
    "directWorkoutComplianceScore": 64,
    "moderateIntensityMinutes": 2,
    "vigorousIntensityMinutes": 33,
    "steps": 5882,
    "beginPotentialStamina": 100.0,
    "endPotentialStamina": 78.0,
    "minAvailableStamina": 78.0,
    "differenceBodyBattery": -9
  },
  "connectIQMeasurements": [
    {
      "appID": "7c83d402-4b68-4f0a-b167-7139788a19b3",
      "developerFieldNumber": 6,
      "value": "0.0"
    },
    {
      "appID": "7c83d402-4b68-4f0a-b167-7139788a19b3",
      "developerFieldNumber": 4,
      "value": "162.0"
    },
    {
      "appID": "7c83d402-4b68-4f0a-b167-7139788a19b3",
      "developerFieldNumber": 7,
      "value": "55058.0"
    },
    {
      "appID": "7c83d402-4b68-4f0a-b167-7139788a19b3",
      "developerFieldNumber": 2,
      "value": "32.0"
    }
  ]
}